setup.py
dsnd_distributions_sunil/Binomialdistribution.py
dsnd_distributions_sunil/Gaussiandistribution.py
dsnd_distributions_sunil/Generaldistribution.py
dsnd_distributions_sunil/__init__.py
dsnd_distributions_sunil.egg-info/PKG-INFO
dsnd_distributions_sunil.egg-info/SOURCES.txt
dsnd_distributions_sunil.egg-info/dependency_links.txt
dsnd_distributions_sunil.egg-info/not-zip-safe
dsnd_distributions_sunil.egg-info/top_level.txt