Metadata-Version: 1.0
Name: dsnd-distributions-sunil
Version: 1.0
Summary: Gaussian and Binomial distributions by Sunil
Home-page: UNKNOWN
Author: Sunil Thakur
Author-email: sunilforu@gmail.com
License: UNKNOWN
Platform: UNKNOWN
